microimpute/__init__.py
microimpute/config.py
microimpute/comparisons/__init__.py
microimpute/comparisons/autoimpute.py
microimpute/comparisons/autoimpute_helpers.py
microimpute/comparisons/imputations.py
microimpute/comparisons/metrics.py
microimpute/comparisons/validation.py
microimpute/evaluations/__init__.py
microimpute/evaluations/cross_validation.py
microimpute/evaluations/predictor_analysis.py
microimpute/models/__init__.py
microimpute/models/imputer.py
microimpute/models/matching.py
microimpute/models/mdn.py
microimpute/models/ols.py
microimpute/models/qrf.py
microimpute/models/quantreg.py
microimpute/utils/__init__.py
microimpute/utils/dashboard_formatter.py
microimpute/utils/data.py
microimpute/utils/statmatch_hotdeck.py
microimpute/utils/type_handling.py
microimpute/visualizations/__init__.py
microimpute/visualizations/comparison_plots.py
microimpute/visualizations/performance_plots.py
microimpute-1.13.0.dist-info/METADATA
microimpute-1.13.0.dist-info/WHEEL
microimpute-1.13.0.dist-info/top_level.txt
microimpute-1.13.0.dist-info/RECORD
